LICENSE
README.md
setup.py
greeclimateapi/__init__.py
greeclimateapi/enums.py
greeclimateapi/greeClimateApi.py
greeclimateapi/greeStatusData.py
greeclimateapi.egg-info/PKG-INFO
greeclimateapi.egg-info/SOURCES.txt
greeclimateapi.egg-info/dependency_links.txt
greeclimateapi.egg-info/requires.txt
greeclimateapi.egg-info/top_level.txt
greeclimateapi/commands/__init__.py
greeclimateapi/commands/bindGreeCommand.py
greeclimateapi/commands/cipher.py
greeclimateapi/commands/factory.py
greeclimateapi/commands/greeCommand.py
greeclimateapi/commands/greeSetCommands.py
greeclimateapi/commands/primitivies.py
greeclimateapi/commands/scanGreeCommand.py
greeclimateapi/commands/statusGreeCommand.py