Metadata-Version: 2.2
Name: greeclimateapi
Version: 0.3.0
Summary: Gree API
Home-page: https://github.com/matizk144/greeclimateapi
Author: matizk144
Author-email: matizk@gmail.com
License: MIT
Classifier: Programming Language :: Python :: 3
Classifier: License :: OSI Approved :: MIT License
Classifier: Operating System :: OS Independent
Requires-Python: >=3.6
License-File: LICENSE
Requires-Dist: pycryptodome
Dynamic: author
Dynamic: author-email
Dynamic: classifier
Dynamic: home-page
Dynamic: license
Dynamic: requires-dist
Dynamic: requires-python
Dynamic: summary
